imbibed/imbibed.py
imbibed-0.1.0.dist-info/LICENSE
imbibed-0.1.0.dist-info/METADATA
imbibed-0.1.0.dist-info/WHEEL
imbibed-0.1.0.dist-info/entry_points.txt
imbibed-0.1.0.dist-info/top_level.txt
imbibed-0.1.0.dist-info/RECORD
